llama_index/readers/awadb/__init__.py
llama_index/readers/awadb/base.py
llama_index_readers_awadb-0.4.0.dist-info/METADATA
llama_index_readers_awadb-0.4.0.dist-info/WHEEL
llama_index_readers_awadb-0.4.0.dist-info/licenses/LICENSE
llama_index_readers_awadb-0.4.0.dist-info/RECORD
